MANIFEST.in
README.md
requirements.txt
setup.py
karakuri/__init__.py
karakuri/project.py
karakuri/run.py
karakuri.egg-info/PKG-INFO
karakuri.egg-info/SOURCES.txt
karakuri.egg-info/dependency_links.txt
karakuri.egg-info/entry_points.txt
karakuri.egg-info/requires.txt
karakuri.egg-info/top_level.txt