Metadata-Version: 1.1
Name: karakuri
Version: 0.2.6
Summary: Task management tool for docker image
Home-page: http://github.com/rail44/karakuri
Author: Satoshi Amemiya
Author-email: satoshi_amemiya@voyagegroup.com
License: BSD
Keywords: docker
Platform: UNKNOWN
Classifier: Development Status :: 3 - Alpha
Classifier: Topic :: Utilities
Classifier: License :: OSI Approved :: BSD License
